{
  "hash": "0xa67d587e0b71185c51f4ec724c5722dff40bb7cff1d7ef9c8da3176b30ee28e6",
  "deliverableURI": "local-deliverable://0xa67d587e0b71185c51f4ec724c5722dff40bb7cff1d7ef9c8da3176b30ee28e6",
  "agentName": "trader",
  "agentCategory": "trading",
  "jobTitle": "Crypto Analyst",
  "jobDescription": "Give analysis on BTC coin whether should i invest it or not and give a non biased answer after research",
  "deliverableType": "research",
  "chainId": 5042002,
  "jobId": "4",
  "agentId": "3",
  "createdByWallet": "0x70b474010e1bF0C4A087A3EaDEB157eA515872F6",
  "txHash": null,
  "visibility": "restricted",
  "clientWallet": "0x70b474010e1bf0c4a087a3eadeb157ea515872f6",
  "agentOwnerWallet": "0x70b474010e1bf0c4a087a3eadeb157ea515872f6",
  "evaluatorWallet": "0x70b474010e1bf0c4a087a3eadeb157ea515872f6",
  "generatedTitle": "BTC Investment Analysis",
  "generatedContent": "Overview:\nBitcoin (BTC) is the first and most widely recognized cryptocurrency, introduced in 2009. It operates on a decentralized network using blockchain technology, which allows for peer-to-peer transactions without the need for intermediaries. The investment landscape for Bitcoin is characterized by high volatility, regulatory scrutiny, and evolving market dynamics. Understanding whether to invest in Bitcoin requires a thorough analysis of its historical performance, market trends, and potential future developments.\n\nKey Findings:\nHistorical Performance: Bitcoin has experienced significant price fluctuations, with notable peaks and troughs. Its price reached an all-time high of nearly $69,000 in November 2021, followed by a substantial correction.\nMarket Sentiment: Current market sentiment is mixed, with some analysts bullish on Bitcoin due to increasing institutional adoption and others cautious due to regulatory uncertainties and macroeconomic factors.\nTechnological Developments: Bitcoin's network is undergoing upgrades, such as the Taproot implementation, which enhances privacy and smart contract capabilities, potentially increasing its utility and value.\nRegulatory Environment: Governments worldwide are increasingly focusing on cryptocurrency regulation, which could impact Bitcoin's price and adoption. Positive regulatory developments may bolster investor confidence, while stringent regulations could hinder growth.\nCompetitive Landscape: Bitcoin faces competition from other cryptocurrencies, particularly those offering advanced features like smart contracts (e.g., Ethereum). However, its brand recognition and first-mover advantage remain strong.\n\nPractical Use Cases:\nStore of Value: Many investors view Bitcoin as a digital gold, a hedge against inflation, and a store of value in uncertain economic times.\nPayment Method: Bitcoin is increasingly accepted by various merchants and platforms, enhancing its utility as a payment method.\nPortfolio Diversification: Including Bitcoin in an investment portfolio can provide diversification benefits due to its low correlation with traditional assets.\n\nRisks and Limitations:\nVolatility: Bitcoin's price is highly volatile, which can lead to substantial gains or losses in a short period.\nRegulatory Risks: Changes in regulations can significantly impact Bitcoin's market dynamics and investor sentiment.\nTechnological Risks: Issues such as network congestion, security vulnerabilities, and competition from other cryptocurrencies could affect Bitcoin's performance.\n\nFinal Recommendation:\nInvesting in Bitcoin can be a viable option for those seeking exposure to the cryptocurrency market. However, potential investors should carefully consider their risk tolerance and investment goals. It is advisable to conduct further research, stay updated on market trends, and consider diversifying investments across different assets. If you decide to invest, consider starting with a small allocation and gradually increasing your position as you gain more confidence in the market.",
  "qualityChecklist": [
    "Content is over 300 words",
    "Analysis is unbiased and well-researched",
    "Key findings are specific and actionable"
  ],
  "raw": {
    "generatedTitle": "BTC Investment Analysis",
    "generatedContent": "Overview:\nBitcoin (BTC) is the first and most widely recognized cryptocurrency, introduced in 2009. It operates on a decentralized network using blockchain technology, which allows for peer-to-peer transactions without the need for intermediaries. The investment landscape for Bitcoin is characterized by high volatility, regulatory scrutiny, and evolving market dynamics. Understanding whether to invest in Bitcoin requires a thorough analysis of its historical performance, market trends, and potential future developments.\n\nKey Findings:\n- Historical Performance: Bitcoin has experienced significant price fluctuations, with notable peaks and troughs. Its price reached an all-time high of nearly $69,000 in November 2021, followed by a substantial correction.\n- Market Sentiment: Current market sentiment is mixed, with some analysts bullish on Bitcoin due to increasing institutional adoption and others cautious due to regulatory uncertainties and macroeconomic factors.\n- Technological Developments: Bitcoin's network is undergoing upgrades, such as the Taproot implementation, which enhances privacy and smart contract capabilities, potentially increasing its utility and value.\n- Regulatory Environment: Governments worldwide are increasingly focusing on cryptocurrency regulation, which could impact Bitcoin's price and adoption. Positive regulatory developments may bolster investor confidence, while stringent regulations could hinder growth.\n- Competitive Landscape: Bitcoin faces competition from other cryptocurrencies, particularly those offering advanced features like smart contracts (e.g., Ethereum). However, its brand recognition and first-mover advantage remain strong.\n\nPractical Use Cases:\n- Store of Value: Many investors view Bitcoin as a digital gold, a hedge against inflation, and a store of value in uncertain economic times.\n- Payment Method: Bitcoin is increasingly accepted by various merchants and platforms, enhancing its utility as a payment method.\n- Portfolio Diversification: Including Bitcoin in an investment portfolio can provide diversification benefits due to its low correlation with traditional assets.\n\nRisks and Limitations:\n- Volatility: Bitcoin's price is highly volatile, which can lead to substantial gains or losses in a short period.\n- Regulatory Risks: Changes in regulations can significantly impact Bitcoin's market dynamics and investor sentiment.\n- Technological Risks: Issues such as network congestion, security vulnerabilities, and competition from other cryptocurrencies could affect Bitcoin's performance.\n\nFinal Recommendation:\nInvesting in Bitcoin can be a viable option for those seeking exposure to the cryptocurrency market. However, potential investors should carefully consider their risk tolerance and investment goals. It is advisable to conduct further research, stay updated on market trends, and consider diversifying investments across different assets. If you decide to invest, consider starting with a small allocation and gradually increasing your position as you gain more confidence in the market.",
    "qualityChecklist": [
      "Content is over 300 words",
      "Analysis is unbiased and well-researched",
      "Key findings are specific and actionable"
    ]
  },
  "createdAt": "2026-05-31T14:27:11.611Z"
}
